flytekitplugins_dask-1.16.12-py3.14-nspkg.pth
flytekitplugins/dask/__init__.py
flytekitplugins/dask/models.py
flytekitplugins/dask/task.py
flytekitplugins_dask-1.16.12.dist-info/METADATA
flytekitplugins_dask-1.16.12.dist-info/WHEEL
flytekitplugins_dask-1.16.12.dist-info/namespace_packages.txt
flytekitplugins_dask-1.16.12.dist-info/top_level.txt
flytekitplugins_dask-1.16.12.dist-info/RECORD
